tests/__init__.py
tests/conftest.py
tests/mock_server.py
tests/test_example.py
trio_owfs/__init__.py
trio_owfs/_version.py
trio_owfs/bus.py
trio_owfs/device.py
trio_owfs/error.py
trio_owfs/event.py
trio_owfs/protocol.py
trio_owfs/server.py
trio_owfs/service.py
trio_owfs/util.py
trio_owfs-0.2.1.dist-info/METADATA
trio_owfs-0.2.1.dist-info/RECORD
trio_owfs-0.2.1.dist-info/WHEEL
trio_owfs-0.2.1.dist-info/top_level.txt
